comtypes/GUID.py
comtypes/__init__.py
comtypes/_comobject.py
comtypes/_memberspec.py
comtypes/_meta.py
comtypes/_npsupport.py
comtypes/_safearray.py
comtypes/_tlib_version_checker.py
comtypes/_vtbl.py
comtypes/automation.py
comtypes/clear_cache.py
comtypes/connectionpoints.py
comtypes/errorinfo.py
comtypes/git.py
comtypes/hints.pyi
comtypes/hresult.py
comtypes/logutil.py
comtypes/malloc.py
comtypes/messageloop.py
comtypes/patcher.py
comtypes/persist.py
comtypes/safearray.py
comtypes/shelllink.py
comtypes/stream.py
comtypes/typeinfo.py
comtypes/util.py
comtypes/viewobject.py
comtypes/_post_coinit/__init__.py
comtypes/_post_coinit/_cominterface_meta_patcher.py
comtypes/_post_coinit/activeobj.py
comtypes/_post_coinit/bstr.py
comtypes/_post_coinit/instancemethod.py
comtypes/_post_coinit/misc.py
comtypes/_post_coinit/unknwn.py
comtypes/client/__init__.py
comtypes/client/_activeobj.py
comtypes/client/_code_cache.py
comtypes/client/_constants.py
comtypes/client/_create.py
comtypes/client/_events.py
comtypes/client/_generate.py
comtypes/client/_managing.py
comtypes/client/dynamic.py
comtypes/client/lazybind.py
comtypes/server/__init__.py
comtypes/server/automation.py
comtypes/server/connectionpoints.py
comtypes/server/inprocserver.py
comtypes/server/localserver.py
comtypes/server/register.py
comtypes/server/w_getopt.py
comtypes/test/TestComServer.idl
comtypes/test/TestComServer.py
comtypes/test/TestComServer.tlb
comtypes/test/TestDispServer.idl
comtypes/test/TestDispServer.py
comtypes/test/TestDispServer.tlb
comtypes/test/__init__.py
comtypes/test/find_memleak.py
comtypes/test/monikers_helper.py
comtypes/test/mylib.idl
comtypes/test/mylib.tlb
comtypes/test/mytypelib.idl
comtypes/test/runtests.py
comtypes/test/setup.py
comtypes/test/test_BSTR.py
comtypes/test/test_DISPPARAMS.py
comtypes/test/test_GUID.py
comtypes/test/test_QueryService.py
comtypes/test/test_agilent.py
comtypes/test/test_avmc.py
comtypes/test/test_basic.py
comtypes/test/test_bctx.py
comtypes-1.4.15.dist-info/licenses/LICENSE.txt
comtypes-1.4.15.dist-info/METADATA
comtypes-1.4.15.dist-info/WHEEL
comtypes-1.4.15.dist-info/entry_points.txt
comtypes-1.4.15.dist-info/top_level.txt
comtypes-1.4.15.dist-info/RECORD
