Metadata-Version: 2.4
Name: comtypes
Version: 1.4.15
Summary: Pure Python COM package
Author-email: Thomas Heller <theller@python.net>
License-Expression: MIT
Project-URL: Source, https://github.com/enthought/comtypes
Project-URL: Download, https://github.com/enthought/comtypes/releases
Project-URL: Issues, https://github.com/enthought/comtypes/issues
Classifier: Development Status :: 5 - Production/Stable
Classifier: Intended Audience :: Developers
Classifier: Operating System :: Microsoft :: Windows
Classifier: Programming Language :: Python
Classifier: Programming Language :: Python :: 3
Classifier: Topic :: Software Development :: Libraries :: Python Modules
Requires-Python: >=3.9
License-File: LICENSE.txt
Dynamic: license-file
